Rypple/__init__.py
Rypple/decorators.py
Rypple/exceptions.py
Rypple/extension.py
Rypple/namespace.py
Rypple/scope.py
Rypple/step.py
Rypple/extensions/console.py
Rypple/extensions/core.py
Rypple/extensions/filesystem.py
Rypple/extensions/rypile/c#.py
Rypple/extensions/rypile/c++.py
Rypple/extensions/rypile/c.py
Rypple/extensions/rypile/core.py
Rypple/extensions/rypile/gradle.py
Rypple/extensions/rypile/java.py
Rypple/extensions/rypile/javascript.py
Rypple/extensions/rypile/kotlin.py
Rypple/extensions/rypile/lua.py
Rypple/extensions/rypile/msbuild.py
Rypple/extensions/rypile/python.py
Rypple-0.1.2.dist-info/LICENSE
Rypple-0.1.2.dist-info/METADATA
Rypple-0.1.2.dist-info/WHEEL
Rypple-0.1.2.dist-info/top_level.txt
Rypple-0.1.2.dist-info/RECORD
