Metadata-Version: 2.1
Name: Rypple
Version: 0.1.2
Author-email: Anthony Markovitz <anthonym6013@gmail.com>
Project-URL: Homepage, https://github.com/A-t-l-i-s/Rypple
Project-URL: Bug Tracker, https://github.com/A-t-l-i-s/Rypple/issues
Requires-Python: >=3
License-File: LICENSE
Requires-Dist: colorama
Requires-Dist: orjson
